logger
rp_generator
